[
  {
    "scale_left": "Worst Star Wars Movie",
    "scale_right": "Best Star Wars Movie"
  },
  {
    "scale_left": "Least Favorite Star Wars Character",
    "scale_right": "Most Favorite Star Wars Character"
  },
  {
    "scale_left": "Worst Star Wars Video Game",
    "scale_right": "Best Star Wars Video Game"
  },
  {
    "scale_left": "Worst Game We've Played as a Group",
    "scale_right": "Best Game We've Played as a Group"
  },
  {
    "scale_left": "Worst Wordle Starting Word",
    "scale_right": "Best Wordle Starting Word"
  },
  {
    "scale_left": "Worst Place in Colorado",
    "scale_right": "Best Place in Colorado"
  },
  {
    "scale_left": "Worst Place to Vacation",
    "scale_right": "Best Place to Vacation"
  },
  {
    "scale_left": "Least Garry Place to Vacation",
    "scale_right": "Most Garry Place to Vacation"
  },
  {
    "scale_left": "Least Garry Phase of Garrett's Life",
    "scale_right": "Most Garry Phase of Garrett's Life"
  },
  {
    "scale_left": "Least Useful League Champion",
    "scale_right": "Most Useful League Champion"
  },
  {
    "scale_left": "Dumbest League Champion",
    "scale_right": "Smartest League Champion"
  },
  {
    "scale_left": "Least Garry League Champion",
    "scale_right": "Smartest League Champion"
  },
  {
    "scale_left": "Worst Pet",
    "scale_right": "Best Pet"
  },
  {
    "scale_left": "Not Garry",
    "scale_right": "Garry"
  },
  {
    "scale_left": "Worst Thing to Get Tattooed",
    "scale_right": "Best Thing to Get Tattooed"
  },
  {
    "scale_left": "Worst Way to Commit Murder and Get Away With It",
    "scale_right": "Best Way to Commit Murder and Get Away With It"
  },
  {
    "scale_left": "Worst Way to Make Money",
    "scale_right": "Best Way to Make Money"
  },
  {
    "scale_left": "Least Garry to Make Money",
    "scale_right": "Most Garry to Make Money"
  },
  {
    "scale_left": "Worst Person/Character/Creature to Watch Have Sex",
    "scale_right": "Best Person/Character/Creature to Watch Have Sex"
  },
  {
    "scale_left": "Least Likely Thing to Do if Homeless and No Money",
    "scale_right": "Most Likely Thing to Do if Homeless and No Money"
  },
  {
    "scale_left": "Least Successful Dating Profile Item",
    "scale_right": "Most Successful Dating Profile Item"
  },
  {
    "scale_left": "Least Garry Dating Profile Item",
    "scale_right": "Most Garry Dating Profile Item"
  },
  {
    "scale_left": "Least Desirable Fictional Character Fight to Watch",
    "scale_right": "Most Desirable Fictional Character Fight to Watch"
  },
  {
    "scale_left": "Worst Thing to Happen After Winning a Million Dollars",
    "scale_right": "Best Thing to Happen After Winning a Million Dollars"
  },
  {
    "scale_left": "Least Stressful Scenario",
    "scale_right": "Most Stressful Scenario"
  },
  {
    "scale_left": "Least Attractive Female Celebrity",
    "scale_right": "Most Attractive Female Celebrity"
  },
  {
    "scale_left": "Least Attractive Male Celebrity",
    "scale_right": "Most Attractive Male Celebrity"
  },
  {
    "scale_left": "Least Important Social Issue",
    "scale_right": "Most Important Social Issue"
  },
  {
    "scale_left": "Least Desirable Fantasy Creature to Have Sex With",
    "scale_right": "Most Desirable Fantasy Creature to Have Sex With"
  },
  {
    "scale_left": "Worst Place to Hide a Body",
    "scale_right": "Best Place to Hide a Body"
  },
  {
    "scale_left": "Worst Thing to Share on Social Media",
    "scale_right": "Best Thing to Share on Social Media"
  },
  {
    "scale_left": "Worst Way to Propose Marriage",
    "scale_right": "Best Way to Propose Marriage"
  },
  {
    "scale_left": "Least Garry Way to Propose Marriage",
    "scale_right": "Most Garry Way to Propose Marriage"
  },
  {
    "scale_left": "Worst High School Experience",
    "scale_right": "Best High School Experience"
  },
  {
    "scale_left": "Garrett's Worst High School Experience",
    "scale_right": "Garett's Best High School Experience"
  },
  {
    "scale_left": "Least Likely Thing for a Cult to Worship",
    "scale_right": "Most Likely Thing for a Cult to Worship"
  },
  {
    "scale_left": "Worst Way to Get Everyone's Attention",
    "scale_right": "Best Way to Get Everyone's Attention"
  },
  {
    "scale_left": "Worst Thing to Lie About",
    "scale_right": "Best Thing to Lie About"
  },
  {
    "scale_left": "Easiest Thing to Steal",
    "scale_right": "Hardest Thing to Steal"
  },
  {
    "scale_left": "Least Garry Thing to Steal",
    "scale_right": "Most Garry Thing to Steal"
  },
  {
    "scale_left": "Least Painful Thing",
    "scale_right": "Most Painful Thing"
  },
  {
    "scale_left": "Fictional Character with Easiest Life",
    "scale_right": "Fictional Character with Hardest Life"
  },
  {
    "scale_left": "Least Important Problem for Humanity to Solve",
    "scale_right": "Most Important Problem for Humanity to Solve"
  },
  {
    "scale_left": "Least Important Problem for Garry to Solve",
    "scale_right": "Most Important Problem for Garry to Solve"
  },
  {
    "scale_left": "Worst Thing to Use for Blackmail",
    "scale_right": "Best Thing to Use for Blackmail"
  },
  {
    "scale_left": "Least Garry Thing to Use for Blackmail",
    "scale_right": "Most Garry Thing to Use for Blackmail"
  }
]